{"stat.breakItem.minecraft.stone_sword":1,"stat.crouchOneCm":1741,"stat.useItem.minecraft.chest":4,"stat.mineBlock.minecraft.furnace":2,"stat.craftItem.minecraft.iron_helmet":1,"stat.craftItem.minecraft.wooden_pickaxe":1,"stat.killEntity.Sheep":4,"stat.mineBlock.minecraft.sand":1,"stat.useItem.minecraft.cobblestone":121,"achievement.exploreAllBiomes":{"value":0,"progress":["Roofed Forest M","Forest","Desert","Desert M","Birch Forest M","Taiga","DesertHills","Ocean","Extreme Hills","Plains","Beach","Birch Forest","Roofed Forest","River"]},"stat.craftItem.minecraft.cooked_chicken":10,"stat.craftItem.minecraft.iron_pickaxe":1,"stat.craftItem.minecraft.iron_chestplate":1,"stat.craftItem.minecraft.chest":4,"achievement.acquireIron":26,"achievement.openInventory":76,"stat.craftItem.minecraft.furnace":5,"stat.damageDealt":15080,"stat.craftItem.minecraft.torch":108,"stat.mineBlock.minecraft.log":34,"stat.killEntity.Bat":3,"stat.useItem.minecraft.cooked_mutton":6,"stat.fallOneCm":11056,"stat.mineBlock.minecraft.diamond_ore":14,"stat.flyOneCm":5120,"achievement.buildPickaxe":9,"stat.mineBlock.minecraft.torch":3,"stat.mineBlock.minecraft.iron_ore":130,"achievement.buildFurnace":4,"stat.damageTaken":872,"stat.useItem.minecraft.cooked_chicken":9,"stat.useItem.minecraft.boat":1,"stat.useItem.minecraft.torch":113,"stat.craftItem.minecraft.coal":87,"stat.useItem.minecraft.stone_pickaxe":924,"stat.craftItem.minecraft.cooked_mutton":6,"stat.breakItem.minecraft.wooden_pickaxe":1,"stat.craftItem.minecraft.stone_axe":2,"stat.killEntity.Chicken":18,"stat.craftItem.minecraft.stone_pickaxe":7,"stat.mineBlock.minecraft.cobblestone":3,"stat.mineBlock.minecraft.gold_ore":8,"achievement.buildWorkBench":2,"stat.useItem.minecraft.stone":11,"stat.useItem.minecraft.furnace":7,"stat.breakItem.minecraft.stone_pickaxe":7,"stat.craftItem.minecraft.iron_leggings":1,"stat.useItem.minecraft.stone_sword":239,"stat.climbOneCm":6872,"stat.mineBlock.minecraft.stone_stairs":6,"stat.useItem.minecraft.sapling":5,"stat.drop":2,"achievement.buildHoe":1,"stat.craftItem.minecraft.boat":1,"achievement.mineWood":402,"stat.craftItem.minecraft.iron_axe":1,"stat.mineBlock.minecraft.red_flower":1,"stat.mineBlock.minecraft.crafting_table":1,"achievement.killEnemy":51,"stat.useItem.minecraft.iron_axe":196,"stat.mineBlock.minecraft.cactus":2,"achievement.diamonds":13,"stat.killEntity.Creeper":2,"stat.craftItem.minecraft.diamond_pickaxe":1,"stat.useItem.minecraft.crafting_table":3,"stat.playOneMinute":242464,"stat.craftItem.minecraft.gold_ingot":8,"stat.useItem.minecraft.stone_hoe":10,"stat.killEntity.Pig":4,"stat.useItem.minecraft.stone_shovel":49,"stat.killEntity.Enderman":2,"stat.leaveGame":5,"stat.diveOneCm":5501,"stat.craftItem.minecraft.iron_ingot":129,"achievement.buildBetterPickaxe":9,"stat.killEntity.Spider":1,"stat.craftItem.minecraft.stone_stairs":84,"stat.mineBlock.minecraft.sapling":1,"stat.timeSinceDeath":242464,"stat.craftItem.minecraft.cooked_porkchop":3,"stat.craftItem.minecraft.stone_shovel":1,"stat.mineBlock.minecraft.leaves2":11,"stat.mineBlock.minecraft.leaves":26,"stat.craftItem.minecraft.stick":88,"stat.boatOneCm":82444,"achievement.buildSword":2,"stat.useItem.minecraft.fishing_rod":5,"stat.swimOneCm":53860,"stat.killEntity.Skeleton":9,"stat.walkOneCm":1402154,"stat.mineBlock.minecraft.coal_ore":180,"stat.craftItem.minecraft.stone_hoe":1,"stat.mineBlock.minecraft.lapis_ore":11,"stat.mineBlock.minecraft.log2":434,"stat.jump":1395,"stat.mineBlock.minecraft.tallgrass":91,"stat.craftItem.minecraft.stone_sword":2,"stat.useItem.minecraft.stone_axe":264,"stat.mineBlock.minecraft.gravel":25,"stat.craftItem.minecraft.crafting_table":2,"stat.mobKills":81,"stat.craftItem.minecraft.clock":1,"stat.mineBlock.minecraft.stone":845,"stat.useItem.minecraft.stone_stairs":84,"stat.craftItem.minecraft.planks":96,"stat.killEntity.Zombie":37,"stat.mineBlock.minecraft.redstone_ore":48,"stat.mineBlock.minecraft.dirt":48,"stat.useItem.minecraft.wooden_pickaxe":60,"stat.useItem.minecraft.iron_pickaxe":271,"stat.craftItem.minecraft.iron_boots":1,"stat.breakItem.minecraft.stone_axe":2,"stat.sprintOneCm":4275,"stat.useItem.minecraft.dirt":19}