{"stat.damageDealt":10,"achievement.exploreAllBiomes":{"value":0,"progress":["Forest","Desert","Extreme Hills","Plains","River"]},"achievement.openInventory":5,"stat.useItem.minecraft.minecart":3,"stat.talkedToVillager":1,"stat.fallOneCm":2334,"stat.flyOneCm":4819,"stat.mineBlock.minecraft.torch":1,"stat.climbOneCm":1670,"stat.hopperInspected":2,"stat.damageTaken":144,"stat.useItem.minecraft.torch":1,"stat.timeSinceDeath":15595,"stat.leaveGame":1,"stat.playOneMinute":15595,"stat.walkOneCm":103697,"stat.jump":66,"stat.minecartOneCm":190531,"stat.chestOpened":9,"stat.sprintOneCm":38526}