{"stat.mineBlock.minecraft.stonebrick":982,"stat.useItem.minecraft.nether_wart":126,"stat.useItem.minecraft.fence_gate":35,"stat.mineBlock.minecraft.netherrack":56942,"stat.enderchestOpened":625,"stat.useItem.minecraft.stone_button":44,"stat.mineBlock.minecraft.glass":345,"stat.craftItem.minecraft.wooden_hoe":4,"stat.craftingTableInteraction":914,"stat.useItem.minecraft.minecart":77,"stat.useItem.minecraft.iron_shovel":51208,"stat.craftItem.minecraft.spruce_door":18,"stat.useItem.minecraft.item_frame":2,"stat.useItem.minecraft.brick_block":4,"stat.craftItem.minecraft.minecart":20,"stat.crouchOneCm":2239232,"stat.useItem.minecraft.shears":597,"stat.breakItem.minecraft.leather_boots":1,"stat.mineBlock.minecraft.red_mushroom":121,"stat.breakItem.minecraft.flint_and_steel":1,"stat.useItem.minecraft.spruce_door":23,"stat.mineBlock.minecraft.yellow_flower":115,"stat.craftItem.minecraft.bowl":4,"stat.breakItem.minecraft.iron_shovel":181,"stat.craftItem.minecraft.golden_rail":60,"stat.useItem.minecraft.chest":296,"stat.mineBlock.minecraft.furnace":101,"stat.craftItem.minecraft.coal_block":1443,"stat.craftItem.minecraft.glass_bottle":78,"stat.useItem.minecraft.stone_brick_stairs":544,"stat.killEntity.Sheep":842,"stat.useItem.minecraft.cobblestone":55441,"stat.craftItem.minecraft.iron_sword":4,"stat.breakItem.minecraft.wooden_axe":1,"stat.breakItem.minecraft.iron_axe":20,"stat.useItem.minecraft.quartz_block":3132,"stat.beaconInteraction":23,"stat.craftItem.minecraft.arrow":812,"achievement.openInventory":24432,"stat.useItem.minecraft.stained_glass":6399,"stat.mineBlock.minecraft.redstone_block":29,"stat.killEntity.Cow":902,"stat.mineBlock.minecraft.web":1388,"stat.breakItem.minecraft.stone_sword":1,"stat.useItem.minecraft.stained_glass_pane":69,"stat.killEntity.Ghast":316,"stat.mineBlock.minecraft.stained_glass":397,"stat.useItem.minecraft.log":3402,"stat.mineBlock.minecraft.noteblock":2,"stat.mineBlock.minecraft.spruce_stairs":3,"stat.craftItem.minecraft.iron_chestplate":15,"stat.mineBlock.minecraft.activator_rail":9,"stat.craftItem.minecraft.slime_ball":45,"stat.craftItem.minecraft.iron_door":9,"stat.useItem.minecraft.red_mushroom":10,"stat.entityKilledBy.Guardian":2,"stat.craftItem.minecraft.furnace":169,"stat.mineBlock.minecraft.log":8955,"achievement.bookcase":8,"stat.useItem.minecraft.obsidian":163,"stat.craftItem.minecraft.leather_helmet":4,"stat.craftItem.minecraft.iron_helmet":22,"stat.useItem.minecraft.ice":440,"stat.mineBlock.minecraft.emerald_ore":43,"stat.mineBlock.minecraft.sandstone_stairs":1,"stat.craftItem.minecraft.carpet":672,"stat.craftItem.minecraft.gold_nugget":783,"stat.useItem.minecraft.brown_mushroom":12,"stat.useItem.minecraft.leaves":370,"stat.craftItem.minecraft.stone_pressure_plate":6,"stat.useItem.minecraft.netherrack":27201,"stat.useItem.minecraft.iron_hoe":158,"achievement.acquireIron":1592,"stat.damageDealt":3609741,"stat.useItem.minecraft.fence":678,"stat.craftItem.minecraft.beacon":4,"stat.craftItem.minecraft.ender_chest":11,"stat.useItem.minecraft.iron_block":163,"stat.killEntity.Bat":16,"stat.mineBlock.minecraft.red_mushroom_block":182,"stat.useItem.minecraft.potato":362,"achievement.exploreAllBiomes":{"value":0,"progress":["Desert","Taiga","Mesa Plateau","Ice Mountains","Swampland M","Birch Forest Hills","Extreme Hills+ M","Taiga M","Jungle M","MushroomIsland","Savanna","Roofed Forest M","Mesa Plateau F","Ice Plains Spikes","Ice Plains","FrozenRiver","Mesa Plateau M","MushroomIslandShore","ForestHills","Forest","Mesa (Bryce)","Mega Spruce Taiga","Beach","Roofed Forest","Stone Beach","Extreme Hills M","Desert M","JungleEdge","Deep Ocean","Extreme Hills","Jungle","Savanna Plateau","DesertHills","Birch Forest","Mesa","Mega Taiga","Savanna M","River","Swampland","Sunflower Plains","Extreme Hills+","Flower Forest","Ocean","Plains","TaigaHills","Hell","Cold Taiga","Birch Forest M","JungleHills","Savanna Plateau M","Cold Beach","Cold Taiga Hills"]},"stat.mineBlock.minecraft.double_plant":751,"stat.craftItem.minecraft.iron_pickaxe":292,"stat.craftItem.minecraft.flint_and_steel":14,"stat.useItem.minecraft.spider_eye":212,"stat.craftItem.minecraft.diamond_chestplate":15,"stat.craftItem.minecraft.wool":1946,"stat.mineBlock.minecraft.golden_rail":124,"stat.craftItem.minecraft.enchanting_table":3,"achievement.cookFish":48,"stat.craftItem.minecraft.repeater":62,"stat.useItem.minecraft.glass_pane":894,"stat.useItem.minecraft.anvil":18,"stat.useItem.minecraft.nether_brick_stairs":15,"stat.craftItem.minecraft.emerald":178,"stat.craftItem.minecraft.bed":8,"stat.craftItem.minecraft.wooden_pickaxe":1,"stat.mineBlock.minecraft.sand":44595,"stat.cakeSlicesEaten":42,"stat.craftItem.minecraft.cooked_chicken":408,"stat.breakItem.minecraft.iron_chestplate":6,"stat.mineBlock.minecraft.monster_egg":33,"stat.mineBlock.minecraft.sandstone":2854,"stat.mineBlock.minecraft.waterlily":18,"stat.craftItem.minecraft.chest":177,"stat.mineBlock.minecraft.redstone_torch":96,"stat.useItem.minecraft.wooden_door":152,"stat.useItem.minecraft.brewing_stand":4,"stat.useItem.minecraft.spruce_fence":9,"stat.trappedChestTriggered":1637,"stat.useItem.minecraft.diamond_pickaxe":765544,"stat.useItem.minecraft.rabbit":40,"stat.mineBlock.minecraft.detector_rail":12,"stat.useItem.minecraft.packed_ice":919,"stat.craftItem.minecraft.fence_gate":19,"stat.useItem.minecraft.sticky_piston":133,"stat.useItem.minecraft.golden_shovel":33,"stat.useItem.minecraft.tnt":124,"stat.craftItem.minecraft.diamond_block":64,"stat.useItem.minecraft.redstone_block":33,"stat.mineBlock.minecraft.brown_mushroom_block":12,"stat.useItem.minecraft.diamond_shovel":108863,"stat.useItem.minecraft.snowball":66,"stat.craftItem.minecraft.torch":13502,"achievement.diamondsToYou":1,"stat.useItem.minecraft.hay_block":170,"stat.breakItem.minecraft.stone_shovel":51,"stat.useItem.minecraft.planks":6119,"stat.talkedToVillager":445,"stat.craftItem.minecraft.ender_eye":10,"achievement.overkill":776,"stat.useItem.minecraft.cooked_chicken":374,"stat.useItem.minecraft.torch":18893,"stat.entityKilledBy.Witch":1,"stat.useItem.minecraft.bed":19,"stat.useItem.minecraft.stone_pickaxe":10687,"stat.mineBlock.minecraft.mycelium":13,"stat.mineBlock.minecraft.clay":61,"stat.mineBlock.minecraft.gold_ore":1642,"stat.mineBlock.minecraft.quartz_stairs":44,"stat.craftItem.minecraft.cauldron":2,"stat.useItem.minecraft.skull":3,"stat.craftItem.minecraft.redstone_block":445,"stat.useItem.minecraft.cooked_fish":654,"achievement.buildWorkBench":308,"stat.useItem.minecraft.stone":44266,"stat.treasureFished":1,"stat.mineBlock.minecraft.lapis_block":22,"stat.craftItem.minecraft.slime":6,"stat.craftItem.minecraft.diamond_sword":15,"stat.craftItem.minecraft.stone_button":24,"stat.craftItem.minecraft.snow":1515,"stat.craftItem.minecraft.iron_leggings":7,"stat.useItem.minecraft.ladder":65,"stat.breakItem.minecraft.iron_boots":3,"stat.craftItem.minecraft.diamond_leggings":12,"achievement.killCow":648,"stat.useItem.minecraft.redstone":535,"stat.mineBlock.minecraft.stone_stairs":261,"stat.mineBlock.minecraft.bookshelf":46,"stat.craftItem.minecraft.book":127,"stat.mineBlock.minecraft.slime":36,"stat.mineBlock.minecraft.stone_pressure_plate":25,"stat.useItem.minecraft.noteblock":2,"stat.mineBlock.minecraft.diamond_ore":556,"stat.craftItem.minecraft.hay_block":37,"stat.mineBlock.minecraft.torch":2965,"stat.useItem.minecraft.red_flower":47,"stat.craftItem.minecraft.cooked_beef":661,"stat.useItem.minecraft.milk_bucket":68,"stat.mineBlock.minecraft.tripwire_hook":7,"stat.useItem.minecraft.diamond_sword":29099,"stat.craftItem.minecraft.wooden_pressure_plate":18,"stat.mineBlock.minecraft.brown_mushroom":137,"stat.useItem.minecraft.oak_stairs":291,"stat.craftItem.minecraft.ladder":42,"stat.craftItem.minecraft.wooden_shovel":3,"stat.mineBlock.minecraft.carpet":179,"stat.useItem.minecraft.golden_rail":65,"stat.mineBlock.minecraft.wool":302,"stat.breakItem.minecraft.stone_pickaxe":79,"stat.craftItem.minecraft.lever":15,"stat.useItem.minecraft.rail":671,"stat.useItem.minecraft.enchanting_table":4,"stat.craftItem.minecraft.quartz_block":6283,"stat.climbOneCm":1863927,"stat.useItem.minecraft.stone_sword":226,"achievement.potion":197,"stat.useItem.minecraft.sapling":973,"stat.drop":1782,"stat.mineBlock.minecraft.sea_lantern":129,"stat.mineBlock.minecraft.anvil":8,"stat.fallOneCm":3259888,"stat.craftItem.minecraft.diamond":594,"stat.junkFished":1,"stat.useItem.minecraft.coal_ore":26,"stat.craftItem.minecraft.sandstone":13,"stat.mineBlock.minecraft.nether_brick":812,"stat.hopperInspected":176,"achievement.buildFurnace":267,"stat.useItem.minecraft.cactus":95,"stat.useItem.minecraft.boat":127,"stat.craftItem.minecraft.coal":1671,"stat.craftItem.minecraft.bread":98,"stat.craftItem.minecraft.cooked_mutton":360,"stat.useItem.minecraft.dispenser":12,"stat.breakItem.minecraft.wooden_pickaxe":4,"stat.useItem.minecraft.water_bucket":1584,"stat.craftItem.minecraft.stone_axe":7,"stat.useItem.minecraft.wheat_seeds":850,"stat.mineBlock.minecraft.hopper":26,"stat.useItem.minecraft.yellow_flower":45,"stat.useItem.minecraft.fish":110,"stat.dropperInspected":3,"achievement.enchantments":3,"stat.mineBlock.minecraft.rail":3598,"stat.useItem.minecraft.stonebrick":2145,"stat.mineBlock.minecraft.gold_block":4,"stat.useItem.minecraft.melon_seeds":34,"stat.useItem.minecraft.furnace":247,"stat.breakItem.minecraft.diamond_chestplate":1,"stat.useItem.minecraft.birch_door":50,"stat.useItem.minecraft.trapped_chest":2,"stat.craftItem.minecraft.gold_block":168,"stat.useItem.minecraft.double_plant":30,"stat.useItem.minecraft.hardened_clay":5,"stat.mineBlock.minecraft.tnt":163,"stat.useItem.minecraft.jungle_door":10,"stat.craftItem.minecraft.lead":20,"stat.useItem.minecraft.potion":198,"stat.mineBlock.minecraft.pumpkin":633,"stat.mineBlock.minecraft.end_stone":8,"stat.useItem.minecraft.cooked_mutton":315,"stat.useItem.minecraft.quartz_stairs":316,"stat.useItem.minecraft.melon":1884,"stat.craftItem.minecraft.wooden_button":10,"stat.mineBlock.minecraft.vine":246,"achievement.portal":614,"stat.flyOneCm":4759174,"stat.mineBlock.minecraft.chest":201,"achievement.buildPickaxe":857,"stat.mineBlock.minecraft.packed_ice":1656,"stat.mineBlock.minecraft.birch_fence":6,"stat.mineBlock.minecraft.iron_ore":7427,"stat.mineBlock.minecraft.trapped_chest":6,"stat.craftItem.minecraft.glowstone":334,"stat.useItem.minecraft.prismarine":1182,"stat.damageTaken":116669,"stat.mineBlock.minecraft.prismarine":3606,"stat.useItem.minecraft.wooden_pressure_plate":26,"stat.useItem.minecraft.sponge":703,"stat.entityKilledBy.Spider":1,"stat.useItem.minecraft.cake":3,"stat.useItem.minecraft.red_mushroom_block":102,"stat.mineBlock.minecraft.nether_brick_fence":60,"stat.killEntity.Chicken":898,"stat.craftItem.minecraft.stone_pickaxe":79,"stat.mineBlock.minecraft.cobblestone":22385,"stat.craftItem.minecraft.redstone_lamp":12,"stat.useItem.minecraft.stained_hardened_clay":315,"stat.craftItem.minecraft.netherbrick":1552,"stat.useItem.minecraft.dye":797,"stat.craftItem.minecraft.stained_glass_pane":96,"stat.craftItem.minecraft.leather_boots":2,"stat.mineBlock.minecraft.spruce_fence":1,"stat.craftItem.minecraft.brick_block":70,"stat.breakItem.minecraft.wooden_sword":2,"stat.craftItem.minecraft.melon_seeds":4,"stat.useItem.minecraft.ender_chest":19,"stat.useItem.minecraft.lapis_ore":2,"stat.useItem.minecraft.log2":1083,"stat.useItem.minecraft.flint_and_steel":143,"stat.breakItem.minecraft.diamond_boots":2,"stat.mineBlock.minecraft.enchanting_table":2,"stat.breakItem.minecraft.diamond_shovel":27,"stat.useItem.minecraft.repeater":96,"stat.useItem.minecraft.stone_pressure_plate":11,"stat.craftItem.minecraft.golden_apple":11,"stat.craftItem.minecraft.boat":135,"stat.craftItem.minecraft.iron_hoe":4,"stat.mineBlock.minecraft.wooden_slab":639,"stat.craftItem.minecraft.iron_axe":20,"stat.useItem.minecraft.spruce_stairs":12,"achievement.makeBread":194,"stat.craftItem.minecraft.piston":83,"stat.craftItem.minecraft.mushroom_stew":6,"stat.breakItem.minecraft.iron_sword":4,"stat.useItem.minecraft.stone_slab":1507,"stat.mineBlock.minecraft.fence":2369,"stat.craftItem.minecraft.oak_stairs":244,"stat.useItem.minecraft.cooked_porkchop":263,"stat.mineBlock.minecraft.melon_block":505,"stat.craftItem.minecraft.leather_chestplate":1,"stat.killEntity.Creeper":2345,"stat.craftItem.minecraft.iron_block":620,"stat.mineBlock.minecraft.planks":5197,"stat.useItem.minecraft.lapis_block":62,"stat.dispenserInspected":33,"stat.craftItem.minecraft.stone_slab":2188,"stat.killEntity.Rabbit":266,"stat.useItem.minecraft.hopper":12,"stat.leaveGame":1066,"stat.craftItem.minecraft.iron_ingot":8025,"stat.craftItem.minecraft.stone_stairs":160,"stat.useItem.minecraft.leaves2":85,"stat.killEntity.Endermite":3,"stat.mineBlock.minecraft.leaves":4551,"stat.useItem.minecraft.painting":76,"stat.craftItem.minecraft.hopper":4,"achievement.buildSword":39,"stat.craftItem.minecraft.wooden_door":150,"stat.mineBlock.minecraft.sticky_piston":67,"stat.craftItem.minecraft.birch_fence":12,"achievement.mineWood":10218,"stat.mineBlock.minecraft.red_flower":499,"stat.mineBlock.minecraft.stone_slab":1386,"stat.useItem.minecraft.iron_axe":5286,"stat.useItem.minecraft.snow":1175,"stat.craftItem.minecraft.dye":4501,"stat.mineBlock.minecraft.dropper":3,"stat.craftItem.minecraft.nether_brick_fence":96,"stat.craftItem.minecraft.diamond_pickaxe":105,"stat.useItem.minecraft.stone_shovel":6961,"stat.useItem.minecraft.chicken":51,"stat.breakItem.minecraft.diamond_helmet":2,"stat.useItem.minecraft.iron_ore":21,"stat.diveOneCm":12335114,"stat.useItem.minecraft.lever":80,"stat.craftItem.minecraft.bow":80,"stat.useItem.minecraft.rotten_flesh":3567,"stat.useItem.minecraft.soul_sand":88,"stat.breakItem.minecraft.iron_leggings":4,"stat.craftItem.minecraft.leather":29,"stat.killEntity.Slime":618,"stat.craftItem.minecraft.dispenser":4,"stat.useItem.minecraft.waterlily":4,"stat.mineBlock.minecraft.mossy_cobblestone":459,"stat.useItem.minecraft.nether_brick":755,"stat.craftItem.minecraft.wooden_axe":1,"stat.craftItem.minecraft.sticky_piston":68,"stat.craftItem.minecraft.nether_brick":685,"stat.mineBlock.minecraft.dark_oak_fence_gate":1,"stat.breakItem.minecraft.golden_shovel":1,"stat.useItem.minecraft.bow":4616,"stat.useItem.minecraft.cooked_beef":495,"stat.breakItem.minecraft.diamond_pickaxe":66,"stat.useItem.minecraft.gold_block":4,"stat.mineBlock.minecraft.crafting_table":110,"stat.mineBlock.minecraft.hardened_clay":101,"stat.noteblockPlayed":2,"stat.killEntity.Wolf":10,"stat.craftItem.minecraft.activator_rail":36,"stat.useItem.minecraft.glass_bottle":188,"stat.breakItem.minecraft.diamond_axe":2,"stat.mineBlock.minecraft.cactus":41,"achievement.diamonds":739,"stat.useItem.minecraft.egg":460,"stat.craftItem.minecraft.stonebrick":2412,"stat.useItem.minecraft.crafting_table":318,"stat.craftItem.minecraft.paper":366,"stat.craftItem.minecraft.jungle_door":18,"stat.craftItem.minecraft.bookshelf":45,"stat.craftItem.minecraft.detector_rail":6,"stat.useItem.minecraft.stone_hoe":197,"stat.useItem.minecraft.wooden_hoe":45,"stat.mineBlock.minecraft.obsidian":566,"stat.craftItem.minecraft.diamond_boots":14,"stat.killEntity.Enderman":102,"stat.mineBlock.minecraft.coal_block":23,"stat.craftItem.minecraft.painting":18,"stat.mineBlock.minecraft.stone_brick_stairs":98,"stat.useItem.minecraft.glass":2464,"stat.breakItem.minecraft.wooden_shovel":3,"achievement.buildBetterPickaxe":857,"stat.useItem.minecraft.ender_pearl":45,"stat.mineBlock.minecraft.sapling":62,"stat.timeSinceDeath":9273574,"stat.useItem.minecraft.golden_apple":2,"stat.craftItem.minecraft.cooked_porkchop":661,"stat.useItem.minecraft.gravel":11159,"stat.mineBlock.minecraft.leaves2":704,"stat.killEntity.PigZombie":134,"stat.mineBlock.minecraft.quartz_block":719,"stat.mineBlock.minecraft.jukebox":1,"stat.boatOneCm":13027749,"stat.useItem.minecraft.brown_mushroom_block":3,"stat.useItem.minecraft.golden_sword":222,"stat.useItem.minecraft.wool":486,"stat.useItem.minecraft.mossy_cobblestone":194,"stat.craftItem.minecraft.bucket":65,"stat.entityKilledBy.PigZombie":9,"achievement.buildHoe":14,"stat.useItem.minecraft.nether_brick_fence":83,"stat.craftItem.minecraft.lit_pumpkin":165,"stat.useItem.minecraft.glowstone":372,"stat.craftItem.minecraft.iron_shovel":200,"stat.mineBlock.minecraft.stone_button":22,"stat.useItem.minecraft.reeds":140,"stat.useItem.minecraft.activator_rail":9,"stat.craftItem.minecraft.banner":112,"achievement.killEnemy":13591,"stat.useItem.minecraft.sand":24212,"stat.mineBlock.minecraft.snow_layer":2283,"stat.killEntity.LavaSlime":658,"stat.craftItem.minecraft.fence":225,"stat.playOneMinute":48186399,"stat.useItem.minecraft.redstone_torch":132,"stat.craftItem.minecraft.gold_ingot":2179,"stat.useItem.minecraft.pumpkin_seeds":1,"stat.killEntity.Pig":919,"stat.useItem.minecraft.birch_fence":20,"stat.mineBlock.minecraft.dispenser":16,"stat.noteblockTuned":28,"stat.useItem.minecraft.cooked_rabbit":40,"stat.useItem.minecraft.gold_ore":15,"stat.craftItem.minecraft.golden_shovel":1,"stat.killEntity.Spider":1432,"stat.mineBlock.minecraft.sponge":740,"stat.mineBlock.minecraft.soul_sand":925,"achievement.ghast":63,"stat.craftItem.minecraft.glass":10210,"stat.craftItem.minecraft.stone_shovel":53,"stat.animalsBred":54,"stat.craftItem.minecraft.spruce_stairs":12,"stat.useItem.minecraft.lead":5,"stat.craftItem.minecraft.stick":6236,"stat.entityKilledBy.Skeleton":1,"stat.useItem.minecraft.pumpkin":493,"stat.mineBlock.minecraft.beacon":8,"stat.craftItem.minecraft.wooden_slab":1840,"stat.furnaceInteraction":2944,"stat.useItem.minecraft.mushroom_stew":6,"stat.craftItem.minecraft.baked_potato":139,"stat.playerKills":2,"stat.useItem.minecraft.sandstone":618,"stat.killEntity.Silverfish":36,"stat.mineBlock.minecraft.wooden_button":28,"stat.useItem.minecraft.redstone_ore":32,"stat.craftItem.minecraft.fishing_rod":2,"stat.useItem.minecraft.beef":201,"stat.entityKilledBy.Zombie":4,"stat.useItem.minecraft.stone_axe":1042,"stat.mineBlock.minecraft.quartz_ore":10451,"stat.mineBlock.minecraft.stone":698477,"stat.mineBlock.minecraft.cobblestone_wall":397,"stat.minecartOneCm":5789155,"stat.mineBlock.minecraft.dirt":128692,"stat.mineBlock.minecraft.fence_gate":21,"stat.craftItem.minecraft.brick":311,"stat.useItem.minecraft.wooden_sword":119,"stat.useItem.minecraft.pumpkin_pie":8,"stat.killEntity.Blaze":226,"stat.useItem.minecraft.piston":24,"achievement.onARail":6488,"stat.craftItem.minecraft.redstone_torch":216,"stat.craftItem.minecraft.iron_boots":13,"stat.craftItem.minecraft.anvil":12,"stat.craftItem.minecraft.leather_leggings":1,"stat.useItem.minecraft.dark_oak_door":13,"stat.useItem.minecraft.diamond_axe":17587,"stat.useItem.minecraft.lava_bucket":12,"stat.useItem.minecraft.slime":41,"achievement.blazeRod":104,"achievement.snipeSkeleton":1,"stat.useItem.minecraft.carpet":763,"stat.mineBlock.minecraft.glass_pane":139,"stat.mineBlock.minecraft.spruce_fence_gate":1,"stat.useItem.minecraft.porkchop":201,"stat.useItem.minecraft.wooden_button":39,"stat.mineBlock.minecraft.hay_block":97,"stat.breakItem.minecraft.iron_pickaxe":271,"stat.mineBlock.minecraft.ladder":22,"stat.mineBlock.minecraft.iron_block":266,"stat.useItem.minecraft.cobblestone_wall":104,"stat.craftItem.minecraft.sign":84,"stat.useItem.minecraft.vine":9,"stat.mineBlock.minecraft.gravel":32271,"stat.craftItem.minecraft.blaze_powder":62,"stat.craftItem.minecraft.cooked_rabbit":8,"stat.useItem.minecraft.baked_potato":294,"stat.mineBlock.minecraft.lever":65,"stat.useItem.minecraft.stone_stairs":219,"stat.breakItem.minecraft.iron_helmet":9,"stat.mineBlock.minecraft.redstone_ore":1192,"stat.useItem.minecraft.wooden_axe":64,"stat.tradedWithVillager":195,"stat.useItem.minecraft.wooden_pickaxe":218,"stat.brewingstandInteraction":1,"stat.useItem.minecraft.saddle":3,"stat.craftItem.minecraft.wooden_sword":2,"stat.useItem.minecraft.cauldron":3,"stat.mineBlock.minecraft.ender_chest":11,"stat.killEntity.Squid":19,"stat.useItem.minecraft.mutton":345,"stat.useItem.minecraft.quartz_ore":34,"stat.useItem.minecraft.sea_lantern":123,"stat.killEntity.CaveSpider":82,"stat.craftItem.minecraft.quartz_stairs":264,"stat.useItem.minecraft.fishing_rod":46,"stat.mineBlock.minecraft.coal_ore":24236,"stat.useItem.minecraft.iron_door":10,"stat.useItem.minecraft.bread":202,"stat.mineBlock.minecraft.log2":2561,"stat.mineBlock.minecraft.nether_brick_stairs":2,"stat.craftItem.minecraft.golden_carrot":62,"stat.craftItem.minecraft.diamond_axe":5,"stat.mineBlock.minecraft.wooden_pressure_plate":15,"stat.mineBlock.minecraft.tallgrass":17803,"stat.craftItem.minecraft.redstone":418,"stat.craftItem.minecraft.stone_sword":9,"stat.mineBlock.minecraft.ice":753,"stat.craftItem.minecraft.dropper":1,"stat.useItem.minecraft.iron_sword":1329,"stat.craftItem.minecraft.spruce_fence":9,"achievement.breedCow":2,"stat.useItem.minecraft.coal_block":3,"stat.craftItem.minecraft.sponge":699,"stat.craftItem.minecraft.crafting_table":247,"stat.mobKills":19638,"stat.craftItem.minecraft.diamond_shovel":38,"stat.useItem.minecraft.bucket":1614,"stat.useItem.minecraft.string":20,"stat.killEntity.Zombie":4542,"stat.useItem.minecraft.sign":117,"stat.mineBlock.minecraft.deadbush":7,"stat.breakItem.minecraft.golden_sword":8,"stat.useItem.minecraft.bookshelf":44,"stat.craftItem.minecraft.glass_pane":1152,"stat.useItem.minecraft.banner":120,"stat.useItem.minecraft.detector_rail":21,"stat.craftItem.minecraft.birch_door":57,"stat.useItem.minecraft.carrot":516,"stat.useItem.minecraft.trapdoor":304,"stat.killEntity.Guardian":220,"stat.craftItem.minecraft.dark_oak_door":6,"stat.swimOneCm":9342567,"stat.fishCaught":19,"stat.useItem.minecraft.sandstone_stairs":2,"stat.craftItem.minecraft.nether_brick_stairs":20,"stat.killEntity.Skeleton":2872,"stat.horseOneCm":3089470,"stat.breakItem.minecraft.leather_helmet":5,"stat.walkOneCm":324592652,"stat.mineBlock.minecraft.oak_stairs":105,"stat.mineBlock.minecraft.lapis_ore":311,"stat.craftItem.minecraft.stone_brick_stairs":480,"stat.craftItem.minecraft.stone_hoe":3,"stat.jump":224723,"stat.mineBlock.minecraft.stained_hardened_clay":346,"stat.craftItem.minecraft.stone":36613,"stat.useItem.minecraft.beacon":8,"stat.killEntity.Witch":141,"stat.mineBlock.minecraft.piston":24,"stat.useItem.minecraft.apple":18,"stat.craftItem.minecraft.lapis_block":293,"stat.mineBlock.minecraft.snow":519,"stat.deaths":33,"stat.mineBlock.minecraft.glowstone":848,"stat.useItem.minecraft.wooden_slab":1929,"stat.craftItem.minecraft.clock":3,"stat.mineBlock.minecraft.stained_glass_pane":3,"stat.craftItem.minecraft.planks":13329,"stat.craftItem.minecraft.trapdoor":320,"stat.chestOpened":8163,"stat.itemEnchanted":40,"stat.craftItem.minecraft.shears":12,"stat.craftItem.minecraft.stained_glass":7624,"stat.craftItem.minecraft.diamond_helmet":10,"stat.craftItem.minecraft.cooked_fish":70,"stat.useItem.minecraft.wooden_shovel":181,"stat.useItem.minecraft.iron_pickaxe":72719,"stat.craftItem.minecraft.tnt":813,"stat.breakItem.minecraft.stone_axe":9,"stat.sprintOneCm":68499107,"stat.useItem.minecraft.dirt":97771}