{"stat.mineBlock.minecraft.stonebrick":87,"stat.useItem.minecraft.nether_wart":48,"stat.useItem.minecraft.fence_gate":7,"stat.mineBlock.minecraft.netherrack":43484,"stat.useItem.minecraft.stone_button":27,"stat.mineBlock.minecraft.glass":197,"stat.craftItem.minecraft.wooden_hoe":2,"stat.useItem.minecraft.minecart":16,"stat.useItem.minecraft.iron_shovel":14665,"stat.craftItem.minecraft.spruce_door":15,"stat.craftItem.minecraft.minecart":8,"stat.crouchOneCm":332481,"stat.useItem.minecraft.shears":432,"stat.breakItem.minecraft.leather_boots":1,"stat.mineBlock.minecraft.red_mushroom":33,"stat.breakItem.minecraft.flint_and_steel":1,"stat.useItem.minecraft.spruce_door":13,"stat.mineBlock.minecraft.yellow_flower":44,"stat.craftItem.minecraft.bowl":4,"stat.breakItem.minecraft.iron_shovel":57,"stat.useItem.minecraft.chest":111,"stat.mineBlock.minecraft.furnace":22,"stat.craftItem.minecraft.coal_block":404,"stat.useItem.minecraft.stone_brick_stairs":41,"stat.killEntity.Sheep":580,"stat.useItem.minecraft.cobblestone":14037,"stat.craftItem.minecraft.iron_sword":3,"stat.breakItem.minecraft.wooden_axe":1,"stat.breakItem.minecraft.iron_axe":18,"stat.useItem.minecraft.quartz_block":490,"stat.craftItem.minecraft.arrow":812,"achievement.openInventory":7797,"stat.useItem.minecraft.stained_glass":351,"stat.killEntity.Cow":623,"stat.mineBlock.minecraft.web":404,"stat.breakItem.minecraft.stone_sword":1,"stat.useItem.minecraft.stained_glass_pane":51,"stat.killEntity.Ghast":266,"stat.mineBlock.minecraft.stained_glass":76,"stat.useItem.minecraft.log":1511,"stat.craftItem.minecraft.iron_chestplate":7,"stat.craftItem.minecraft.iron_door":6,"stat.useItem.minecraft.red_mushroom":2,"stat.craftItem.minecraft.furnace":57,"stat.mineBlock.minecraft.log":4142,"achievement.bookcase":8,"stat.useItem.minecraft.obsidian":111,"stat.craftItem.minecraft.leather_helmet":1,"stat.craftItem.minecraft.iron_helmet":14,"stat.useItem.minecraft.ice":440,"stat.mineBlock.minecraft.emerald_ore":35,"stat.craftItem.minecraft.carpet":27,"stat.craftItem.minecraft.gold_nugget":54,"stat.useItem.minecraft.brown_mushroom":7,"stat.useItem.minecraft.leaves":280,"stat.useItem.minecraft.netherrack":21254,"stat.useItem.minecraft.iron_hoe":82,"achievement.acquireIron":471,"stat.damageDealt":1506169,"stat.useItem.minecraft.fence":347,"stat.craftItem.minecraft.ender_chest":5,"stat.killEntity.Bat":7,"stat.mineBlock.minecraft.red_mushroom_block":90,"stat.useItem.minecraft.potato":168,"achievement.exploreAllBiomes":{"value":0,"progress":["Extreme Hills M","Desert","Desert M","JungleEdge","Taiga","Deep Ocean","Extreme Hills","Ice Mountains","Jungle","Swampland M","Savanna Plateau","Birch Forest Hills","Extreme Hills+ M","Taiga M","DesertHills","Jungle M","Birch Forest","Mesa","Savanna M","Savanna","Swampland","River","Roofed Forest M","Sunflower Plains","Extreme Hills+","Mesa Plateau F","Flower Forest","Ocean","TaigaHills","Plains","Ice Plains Spikes","FrozenRiver","Ice Plains","Mesa Plateau M","MushroomIslandShore","Hell","ForestHills","Cold Taiga","Forest","Birch Forest M","JungleHills","Mesa (Bryce)","Beach","Roofed Forest","Stone Beach","Cold Taiga Hills","Cold Beach"]},"stat.mineBlock.minecraft.double_plant":96,"stat.craftItem.minecraft.iron_pickaxe":213,"stat.craftItem.minecraft.flint_and_steel":9,"stat.useItem.minecraft.spider_eye":14,"stat.craftItem.minecraft.diamond_chestplate":5,"stat.craftItem.minecraft.wool":159,"stat.craftItem.minecraft.enchanting_table":2,"achievement.cookFish":12,"stat.craftItem.minecraft.repeater":21,"stat.useItem.minecraft.glass_pane":568,"stat.useItem.minecraft.anvil":6,"stat.useItem.minecraft.nether_brick_stairs":15,"stat.craftItem.minecraft.emerald":5,"stat.craftItem.minecraft.bed":4,"stat.craftItem.minecraft.wooden_pickaxe":1,"stat.mineBlock.minecraft.sand":3560,"stat.craftItem.minecraft.cooked_chicken":377,"stat.breakItem.minecraft.iron_chestplate":4,"stat.mineBlock.minecraft.monster_egg":28,"stat.mineBlock.minecraft.sandstone":1618,"stat.mineBlock.minecraft.waterlily":13,"stat.craftItem.minecraft.chest":76,"stat.mineBlock.minecraft.redstone_torch":9,"stat.useItem.minecraft.wooden_door":55,"stat.useItem.minecraft.spruce_fence":9,"stat.useItem.minecraft.diamond_pickaxe":36389,"stat.useItem.minecraft.rabbit":17,"stat.useItem.minecraft.packed_ice":919,"stat.craftItem.minecraft.fence_gate":1,"stat.useItem.minecraft.sticky_piston":21,"stat.useItem.minecraft.tnt":124,"stat.craftItem.minecraft.diamond_block":20,"stat.mineBlock.minecraft.brown_mushroom_block":12,"stat.useItem.minecraft.diamond_shovel":17698,"stat.useItem.minecraft.snowball":65,"stat.craftItem.minecraft.torch":4446,"stat.useItem.minecraft.hay_block":155,"stat.breakItem.minecraft.stone_shovel":29,"stat.useItem.minecraft.planks":2429,"stat.talkedToVillager":141,"stat.craftItem.minecraft.ender_eye":5,"stat.useItem.minecraft.cooked_chicken":137,"stat.useItem.minecraft.torch":5102,"stat.entityKilledBy.Witch":1,"stat.useItem.minecraft.bed":12,"stat.useItem.minecraft.stone_pickaxe":6730,"stat.mineBlock.minecraft.mycelium":11,"stat.mineBlock.minecraft.clay":23,"stat.mineBlock.minecraft.gold_ore":640,"stat.craftItem.minecraft.cauldron":2,"stat.useItem.minecraft.cooked_fish":52,"achievement.buildWorkBench":216,"stat.useItem.minecraft.stone":10548,"stat.treasureFished":1,"stat.mineBlock.minecraft.lapis_block":6,"stat.craftItem.minecraft.diamond_sword":3,"stat.craftItem.minecraft.stone_button":20,"stat.craftItem.minecraft.snow":1497,"stat.craftItem.minecraft.iron_leggings":4,"stat.useItem.minecraft.ladder":15,"stat.breakItem.minecraft.iron_boots":2,"stat.craftItem.minecraft.diamond_leggings":3,"achievement.killCow":360,"stat.useItem.minecraft.redstone":230,"stat.mineBlock.minecraft.stone_stairs":7,"stat.mineBlock.minecraft.bookshelf":6,"stat.craftItem.minecraft.book":96,"stat.mineBlock.minecraft.stone_pressure_plate":14,"stat.mineBlock.minecraft.diamond_ore":218,"stat.craftItem.minecraft.hay_block":30,"stat.mineBlock.minecraft.torch":459,"stat.useItem.minecraft.red_flower":2,"stat.craftItem.minecraft.cooked_beef":558,"stat.mineBlock.minecraft.tripwire_hook":7,"stat.useItem.minecraft.diamond_sword":12299,"stat.craftItem.minecraft.wooden_pressure_plate":10,"stat.mineBlock.minecraft.brown_mushroom":45,"stat.useItem.minecraft.oak_stairs":36,"stat.craftItem.minecraft.ladder":18,"stat.craftItem.minecraft.wooden_shovel":1,"stat.mineBlock.minecraft.carpet":7,"stat.mineBlock.minecraft.wool":72,"stat.breakItem.minecraft.stone_pickaxe":50,"stat.craftItem.minecraft.lever":2,"stat.useItem.minecraft.rail":10,"stat.useItem.minecraft.enchanting_table":3,"stat.craftItem.minecraft.quartz_block":853,"stat.climbOneCm":191960,"stat.useItem.minecraft.stone_sword":226,"stat.useItem.minecraft.sapling":216,"stat.drop":719,"stat.mineBlock.minecraft.anvil":1,"stat.fallOneCm":993703,"stat.craftItem.minecraft.diamond":180,"stat.junkFished":1,"stat.useItem.minecraft.coal_ore":7,"stat.craftItem.minecraft.sandstone":11,"stat.mineBlock.minecraft.nether_brick":438,"achievement.buildFurnace":80,"stat.useItem.minecraft.boat":95,"stat.craftItem.minecraft.coal":35,"stat.craftItem.minecraft.bread":42,"stat.craftItem.minecraft.cooked_mutton":286,"stat.breakItem.minecraft.wooden_pickaxe":2,"stat.useItem.minecraft.water_bucket":695,"stat.craftItem.minecraft.stone_axe":6,"stat.useItem.minecraft.wheat_seeds":516,"stat.useItem.minecraft.yellow_flower":10,"stat.useItem.minecraft.fish":6,"achievement.enchantments":2,"stat.mineBlock.minecraft.rail":1292,"stat.useItem.minecraft.stonebrick":637,"stat.useItem.minecraft.melon_seeds":17,"stat.useItem.minecraft.furnace":73,"stat.breakItem.minecraft.diamond_chestplate":1,"stat.useItem.minecraft.birch_door":5,"stat.craftItem.minecraft.gold_block":78,"stat.useItem.minecraft.double_plant":6,"stat.useItem.minecraft.hardened_clay":5,"stat.mineBlock.minecraft.tnt":118,"stat.useItem.minecraft.jungle_door":1,"stat.craftItem.minecraft.lead":6,"stat.useItem.minecraft.potion":1,"stat.mineBlock.minecraft.pumpkin":45,"stat.useItem.minecraft.cooked_mutton":78,"stat.craftItem.minecraft.wooden_button":2,"stat.mineBlock.minecraft.vine":128,"achievement.portal":245,"stat.useItem.minecraft.melon":600,"stat.flyOneCm":1547601,"stat.mineBlock.minecraft.chest":43,"achievement.buildPickaxe":511,"stat.mineBlock.minecraft.packed_ice":1655,"stat.mineBlock.minecraft.birch_fence":4,"stat.mineBlock.minecraft.iron_ore":1834,"stat.craftItem.minecraft.glowstone":143,"stat.damageTaken":44914,"stat.useItem.minecraft.wooden_pressure_plate":13,"stat.entityKilledBy.Spider":1,"stat.useItem.minecraft.red_mushroom_block":64,"stat.mineBlock.minecraft.nether_brick_fence":47,"stat.killEntity.Chicken":781,"stat.craftItem.minecraft.stone_pickaxe":50,"stat.mineBlock.minecraft.cobblestone":3316,"stat.craftItem.minecraft.redstone_lamp":12,"stat.useItem.minecraft.stained_hardened_clay":20,"stat.craftItem.minecraft.netherbrick":1424,"stat.useItem.minecraft.dye":388,"stat.craftItem.minecraft.stained_glass_pane":48,"stat.craftItem.minecraft.leather_boots":2,"stat.mineBlock.minecraft.spruce_fence":1,"stat.craftItem.minecraft.brick_block":23,"stat.breakItem.minecraft.wooden_sword":1,"stat.craftItem.minecraft.melon_seeds":4,"stat.useItem.minecraft.ender_chest":8,"stat.useItem.minecraft.log2":257,"stat.useItem.minecraft.flint_and_steel":114,"stat.breakItem.minecraft.diamond_boots":2,"stat.mineBlock.minecraft.enchanting_table":1,"stat.breakItem.minecraft.diamond_shovel":6,"stat.useItem.minecraft.repeater":38,"stat.craftItem.minecraft.golden_apple":11,"stat.craftItem.minecraft.boat":103,"stat.craftItem.minecraft.iron_hoe":3,"stat.craftItem.minecraft.iron_axe":19,"stat.mineBlock.minecraft.wooden_slab":560,"achievement.makeBread":82,"stat.craftItem.minecraft.piston":23,"stat.craftItem.minecraft.mushroom_stew":6,"stat.breakItem.minecraft.iron_sword":3,"stat.useItem.minecraft.stone_slab":588,"stat.mineBlock.minecraft.fence":1236,"stat.craftItem.minecraft.oak_stairs":40,"stat.useItem.minecraft.cooked_porkchop":175,"stat.mineBlock.minecraft.melon_block":186,"stat.craftItem.minecraft.leather_chestplate":1,"stat.killEntity.Creeper":846,"stat.craftItem.minecraft.iron_block":128,"stat.mineBlock.minecraft.planks":2311,"stat.useItem.minecraft.lapis_block":46,"stat.craftItem.minecraft.stone_slab":532,"stat.killEntity.Rabbit":86,"stat.leaveGame":298,"stat.craftItem.minecraft.iron_ingot":2282,"stat.craftItem.minecraft.stone_stairs":116,"stat.mineBlock.minecraft.leaves":2414,"stat.useItem.minecraft.painting":13,"achievement.buildSword":7,"stat.craftItem.minecraft.wooden_door":48,"stat.craftItem.minecraft.birch_fence":12,"stat.mineBlock.minecraft.sticky_piston":9,"achievement.mineWood":4461,"stat.mineBlock.minecraft.red_flower":236,"stat.mineBlock.minecraft.stone_slab":75,"stat.useItem.minecraft.iron_axe":4722,"stat.useItem.minecraft.snow":1054,"stat.craftItem.minecraft.dye":881,"stat.craftItem.minecraft.nether_brick_fence":96,"stat.craftItem.minecraft.diamond_pickaxe":14,"stat.useItem.minecraft.stone_shovel":3918,"stat.useItem.minecraft.chicken":28,"stat.breakItem.minecraft.diamond_helmet":2,"stat.useItem.minecraft.iron_ore":5,"stat.diveOneCm":979754,"stat.useItem.minecraft.lever":19,"stat.craftItem.minecraft.bow":26,"stat.useItem.minecraft.rotten_flesh":631,"stat.useItem.minecraft.soul_sand":35,"stat.breakItem.minecraft.iron_leggings":3,"stat.craftItem.minecraft.leather":3,"stat.killEntity.Slime":105,"stat.useItem.minecraft.waterlily":4,"stat.mineBlock.minecraft.mossy_cobblestone":356,"stat.useItem.minecraft.nether_brick":706,"stat.craftItem.minecraft.wooden_axe":1,"stat.craftItem.minecraft.sticky_piston":13,"stat.craftItem.minecraft.nether_brick":685,"stat.useItem.minecraft.bow":2064,"stat.useItem.minecraft.cooked_beef":204,"stat.breakItem.minecraft.diamond_pickaxe":9,"stat.mineBlock.minecraft.crafting_table":57,"stat.mineBlock.minecraft.hardened_clay":98,"stat.killEntity.Wolf":6,"stat.breakItem.minecraft.diamond_axe":1,"stat.mineBlock.minecraft.cactus":3,"achievement.diamonds":246,"stat.useItem.minecraft.egg":250,"stat.craftItem.minecraft.stonebrick":672,"stat.useItem.minecraft.crafting_table":216,"stat.craftItem.minecraft.paper":303,"stat.craftItem.minecraft.jungle_door":3,"stat.craftItem.minecraft.bookshelf":45,"stat.useItem.minecraft.stone_hoe":115,"stat.useItem.minecraft.wooden_hoe":23,"stat.mineBlock.minecraft.obsidian":350,"stat.craftItem.minecraft.diamond_boots":3,"stat.killEntity.Enderman":31,"stat.craftItem.minecraft.painting":6,"stat.mineBlock.minecraft.stone_brick_stairs":30,"stat.useItem.minecraft.glass":1424,"stat.breakItem.minecraft.wooden_shovel":1,"achievement.buildBetterPickaxe":511,"stat.useItem.minecraft.ender_pearl":4,"stat.mineBlock.minecraft.sapling":11,"stat.timeSinceDeath":2603957,"stat.useItem.minecraft.golden_apple":1,"stat.craftItem.minecraft.cooked_porkchop":545,"stat.useItem.minecraft.gravel":6125,"stat.mineBlock.minecraft.leaves2":152,"stat.killEntity.PigZombie":112,"stat.mineBlock.minecraft.quartz_block":33,"stat.boatOneCm":9999018,"stat.useItem.minecraft.brown_mushroom_block":3,"stat.useItem.minecraft.golden_sword":161,"stat.useItem.minecraft.wool":124,"stat.useItem.minecraft.mossy_cobblestone":3,"stat.craftItem.minecraft.bucket":21,"stat.entityKilledBy.PigZombie":9,"achievement.buildHoe":8,"stat.useItem.minecraft.nether_brick_fence":82,"stat.useItem.minecraft.glowstone":25,"stat.craftItem.minecraft.iron_shovel":63,"stat.mineBlock.minecraft.stone_button":8,"stat.useItem.minecraft.reeds":131,"achievement.killEnemy":5360,"stat.useItem.minecraft.sand":1037,"stat.mineBlock.minecraft.snow_layer":2282,"stat.killEntity.LavaSlime":441,"stat.craftItem.minecraft.fence":24,"stat.playOneMinute":15434539,"stat.useItem.minecraft.redstone_torch":13,"stat.craftItem.minecraft.gold_ingot":619,"stat.killEntity.Pig":699,"stat.useItem.minecraft.birch_fence":16,"stat.mineBlock.minecraft.dispenser":4,"stat.useItem.minecraft.cooked_rabbit":15,"stat.useItem.minecraft.gold_ore":1,"stat.killEntity.Spider":561,"stat.mineBlock.minecraft.soul_sand":781,"achievement.ghast":53,"stat.craftItem.minecraft.glass":1481,"stat.craftItem.minecraft.stone_shovel":30,"stat.animalsBred":38,"stat.useItem.minecraft.lead":2,"stat.craftItem.minecraft.stick":2432,"stat.useItem.minecraft.pumpkin":1,"stat.craftItem.minecraft.wooden_slab":1414,"stat.useItem.minecraft.mushroom_stew":6,"stat.craftItem.minecraft.baked_potato":112,"stat.useItem.minecraft.sandstone":311,"stat.killEntity.Silverfish":30,"stat.mineBlock.minecraft.wooden_button":1,"stat.craftItem.minecraft.fishing_rod":2,"stat.useItem.minecraft.beef":129,"stat.useItem.minecraft.stone_axe":977,"stat.mineBlock.minecraft.quartz_ore":2323,"stat.mineBlock.minecraft.stone":33475,"stat.mineBlock.minecraft.dirt":29717,"stat.minecartOneCm":1104327,"stat.mineBlock.minecraft.fence_gate":6,"stat.craftItem.minecraft.brick":123,"stat.useItem.minecraft.wooden_sword":77,"stat.killEntity.Blaze":85,"stat.craftItem.minecraft.redstone_torch":41,"stat.craftItem.minecraft.iron_boots":6,"stat.craftItem.minecraft.anvil":5,"stat.craftItem.minecraft.leather_leggings":1,"stat.useItem.minecraft.dark_oak_door":5,"stat.useItem.minecraft.diamond_axe":4595,"stat.useItem.minecraft.lava_bucket":7,"achievement.blazeRod":31,"achievement.snipeSkeleton":1,"stat.useItem.minecraft.carpet":36,"stat.mineBlock.minecraft.glass_pane":73,"stat.useItem.minecraft.porkchop":155,"stat.useItem.minecraft.wooden_button":4,"stat.mineBlock.minecraft.hay_block":82,"stat.breakItem.minecraft.iron_pickaxe":207,"stat.mineBlock.minecraft.ladder":14,"stat.craftItem.minecraft.sign":69,"stat.mineBlock.minecraft.gravel":9373,"stat.craftItem.minecraft.blaze_powder":6,"stat.craftItem.minecraft.cooked_rabbit":7,"stat.useItem.minecraft.baked_potato":157,"stat.mineBlock.minecraft.lever":14,"stat.useItem.minecraft.stone_stairs":97,"stat.breakItem.minecraft.iron_helmet":4,"stat.mineBlock.minecraft.redstone_ore":142,"stat.useItem.minecraft.wooden_axe":64,"stat.tradedWithVillager":8,"stat.useItem.minecraft.wooden_pickaxe":109,"stat.useItem.minecraft.saddle":3,"stat.craftItem.minecraft.wooden_sword":2,"stat.useItem.minecraft.cauldron":2,"stat.mineBlock.minecraft.ender_chest":4,"stat.killEntity.Squid":4,"stat.useItem.minecraft.mutton":155,"stat.useItem.minecraft.quartz_ore":30,"stat.killEntity.CaveSpider":26,"stat.useItem.minecraft.fishing_rod":46,"stat.mineBlock.minecraft.coal_ore":4418,"stat.useItem.minecraft.bread":125,"stat.useItem.minecraft.iron_door":8,"stat.mineBlock.minecraft.log2":965,"stat.mineBlock.minecraft.nether_brick_stairs":2,"stat.craftItem.minecraft.golden_carrot":6,"stat.craftItem.minecraft.diamond_axe":2,"stat.mineBlock.minecraft.wooden_pressure_plate":7,"stat.mineBlock.minecraft.tallgrass":2367,"stat.craftItem.minecraft.stone_sword":2,"stat.mineBlock.minecraft.ice":753,"stat.useItem.minecraft.iron_sword":1009,"stat.craftItem.minecraft.spruce_fence":9,"stat.craftItem.minecraft.crafting_table":169,"stat.mobKills":8355,"stat.craftItem.minecraft.diamond_shovel":7,"stat.useItem.minecraft.bucket":716,"stat.useItem.minecraft.string":1,"stat.killEntity.Zombie":1852,"stat.useItem.minecraft.sign":65,"stat.mineBlock.minecraft.deadbush":3,"stat.breakItem.minecraft.golden_sword":6,"stat.useItem.minecraft.bookshelf":26,"stat.craftItem.minecraft.glass_pane":656,"stat.craftItem.minecraft.birch_door":6,"stat.useItem.minecraft.carrot":139,"stat.useItem.minecraft.trapdoor":13,"stat.craftItem.minecraft.dark_oak_door":3,"stat.swimOneCm":2709748,"stat.fishCaught":19,"stat.useItem.minecraft.sandstone_stairs":1,"stat.craftItem.minecraft.nether_brick_stairs":20,"stat.killEntity.Skeleton":1082,"stat.horseOneCm":1750143,"stat.breakItem.minecraft.leather_helmet":1,"stat.walkOneCm":103821570,"stat.mineBlock.minecraft.oak_stairs":6,"stat.mineBlock.minecraft.lapis_ore":66,"stat.craftItem.minecraft.stone_hoe":2,"stat.jump":90744,"stat.mineBlock.minecraft.stained_hardened_clay":285,"stat.craftItem.minecraft.stone":8297,"stat.killEntity.Witch":61,"stat.useItem.minecraft.apple":5,"stat.craftItem.minecraft.lapis_block":56,"stat.mineBlock.minecraft.snow":519,"stat.deaths":13,"stat.mineBlock.minecraft.glowstone":148,"stat.useItem.minecraft.wooden_slab":1702,"stat.craftItem.minecraft.clock":2,"stat.mineBlock.minecraft.stained_glass_pane":3,"stat.craftItem.minecraft.planks":5862,"stat.craftItem.minecraft.trapdoor":12,"stat.craftItem.minecraft.shears":7,"stat.craftItem.minecraft.stained_glass":320,"stat.craftItem.minecraft.diamond_helmet":3,"stat.craftItem.minecraft.cooked_fish":8,"stat.useItem.minecraft.wooden_shovel":60,"stat.useItem.minecraft.iron_pickaxe":54868,"stat.craftItem.minecraft.tnt":44,"stat.breakItem.minecraft.stone_axe":9,"stat.sprintOneCm":21376424,"stat.useItem.minecraft.dirt":31239}